narendra_project/__init__.py
narendra_project/__main__.py
narendra_project-0.2.dist-info/Licence.txt
narendra_project-0.2.dist-info/METADATA
narendra_project-0.2.dist-info/WHEEL
narendra_project-0.2.dist-info/top_level.txt
narendra_project-0.2.dist-info/RECORD
