Metadata-Version: 2.1
Name: narendra-project
Version: 0.2
Summary: package to upload user strategy code using command line interface
Home-page: https://github.com/narendra539804/narendra_package.git
Author: narendra
Author-email: narendranaidu5398@gmail.com
License: UNKNOWN
Platform: UNKNOWN
License-File: Licence.txt
Requires-Dist: maskpass
